bridgepy/__init__.py
bridgepy/bid.py
bridgepy/bridge.py
bridgepy/card.py
bridgepy/datastore.py
bridgepy/entity.py
bridgepy/exception.py
bridgepy/game.py
bridgepy/player.py
bridgepy-0.0.13.dist-info/LICENSE
bridgepy-0.0.13.dist-info/METADATA
bridgepy-0.0.13.dist-info/WHEEL
bridgepy-0.0.13.dist-info/top_level.txt
bridgepy-0.0.13.dist-info/RECORD
