Metadata-Version: 2.2
Name: bridgepy
Version: 0.0.13
Summary: bridgepy is a python package for playing floating bridge!
Home-page: https://github.com/papillonbee/bridgepy
Author: Papan Yongmalwong
Author-email: papillonbee@gmail.com
Keywords: floating bridge,singaporean bridge
Classifier: Programming Language :: Python :: 3
Classifier: License :: OSI Approved :: MIT License
Classifier: Operating System :: OS Independent
Classifier: Topic :: Games/Entertainment
Requires-Python: >=3.10
License-File: LICENSE
Dynamic: author
Dynamic: author-email
Dynamic: classifier
Dynamic: description
Dynamic: description-content-type
Dynamic: home-page
Dynamic: keywords
Dynamic: requires-python
Dynamic: summary
